{
  "title": "Supply Pod",
  "pageId": 5286,
  "revisionId": 8981,
  "wikitext": "'''Supply Pod'''<br />'''Craft''': Imperial Troop Drop Pod<br />'''Affiliation''': Empire<br />'''Era''': Rise of the Empire<br />'''Source''': Rules of Engagement: The Rebel SpecForce Handbook (pages 104)<br />'''Type''': Orbit-to-surface deployment pod<br />'''Scale''': Starfighter<br />'''Length''': 10 meters<br />'''Skill''': None<br />'''Crew''': None<br />'''Passengers''': None<br />'''Cargo Capacity''': 1 metric ton<br />'''Maneuverability''': 3D<br />'''Space''': 10<br />'''Atmosphere''': 415; 1,200 kmh (drop)<br />'''Hull''': 2D<br />'''Weapons''':\n*Self-Destruct Charge\n: Blast Radius: 50/150/300<br />Damage: 4D",
  "category": "transport",
  "license": "CC-BY-SA 3.0",
  "sourceUrl": "http://d6holocron.com/wiki/Supply%20Pod",
  "retrievedAt": "2025-10-10T19:13:50.598Z"
}