{
  "title": "TIE/va Vanguard",
  "pageId": 2023,
  "revisionId": 11792,
  "wikitext": "[[File:TIE-va-Vanguard.JPG|thumb|500px]]\n\n'''TIE/va Vanguard'''<br />'''Craft''': Sienar Fleet Systems TIE/va Vanguard<br />'''Affiliation''': Empire<br />'''Era''': Rebellion<br />'''Type''': Reconnaissance starfighter<br />'''Scale''': Starfighter<br />'''Length''': 6.3 meters<br />'''Skill''': Starfighter piloting: TIE<br />'''Crew''': 1<br />'''Crew Skill''': Starfighter piloting 4D, starship gunnery 3D+1, sensors 4D<br />'''Cargo''': 35 kilograms<br />'''Consumables''': 3 Days<br />'''Maneuverability''': 1D+2<br />'''Space''': 11<br />'''Atmosphere''': 435; 1,350 kmh<br />'''Hull''': 2D+1<br />'''Sensors''':\n*Passive: 25/1D\n*Scan: 60/2D\n*Search: 90/3D\n*Focus: 5/4D+1\n'''Weapons''':\n*2 Laser Cannons (fire-linked)\n: Fire Arc: Front<br />Skill: Starship gunnery<br />Fire Control: 2D<br />Space Range: 1-3/12/25<br />Atmosphere Range: 1-300/1.2/2.5 km<br />Damage: 4D",
  "category": "starfighter",
  "license": "CC-BY-SA 3.0",
  "sourceUrl": "http://d6holocron.com/wiki/TIE%2Fva%20Vanguard",
  "retrievedAt": "2025-10-08T13:07:42.926Z"
}