{
  "title": "Troop Pod",
  "pageId": 5287,
  "revisionId": 8984,
  "wikitext": "'''Troop Pod'''<br />'''Craft''': Imperial Troop Pod<br />'''Affiliation''': Empire<br />'''Era''': Rise of the Empire<br />'''Source''': Rules of Engagement: The Rebel SpecForce Handbook (pages 103-104)<br />'''Type''': Orbit-to-surface deployment pod<br />'''Scale''': Starfighter<br />'''Length''': 10 meters<br />'''Skill''': None<br />'''Crew''': None<br />'''Passengers''': 20<br />'''Cargo Capacity''': 200 kilograms<br />'''Consumables''': 1 day<br />'''Maneuverability''': 3D<br />'''Space''': 10<br />'''Atmosphere''': 415; 1,200 kmh (drop)<br />'''Hull''': 2D<br />\n'''Note:'''\n+2D to sensor operator’s difficulty to identify; failure usually indicates the pod is a meteor or stray hunk of scrap.",
  "category": "transport",
  "license": "CC-BY-SA 3.0",
  "sourceUrl": "http://d6holocron.com/wiki/Troop%20Pod",
  "retrievedAt": "2025-10-10T19:13:59.891Z"
}